kontrol/__init__.py
kontrol/ezca.py
kontrol/logger.py
kontrol/complementary_filter/__init__.py
kontrol/complementary_filter/complementary_filter.py
kontrol/complementary_filter/predefined.py
kontrol/complementary_filter/synthesis.py
kontrol/core/__init__.py
kontrol/core/algorithm.py
kontrol/core/controlutils.py
kontrol/core/foton.py
kontrol/core/math.py
kontrol/core/spectral.py
kontrol/curvefit/__init__.py
kontrol/curvefit/cost.py
kontrol/curvefit/curvefit.py
kontrol/curvefit/error_func.py
kontrol/curvefit/spectrum_fit.py
kontrol/curvefit/transfer_function_fit.py
kontrol/curvefit/model/__init__.py
kontrol/curvefit/model/math_model.py
kontrol/curvefit/model/model.py
kontrol/curvefit/model/transfer_function_model.py
kontrol/dmd/__init__.py
kontrol/dmd/dmd.py
kontrol/dmd/forecast.py
kontrol/dmd/utils.py
kontrol/frequency_series/__init__.py
kontrol/frequency_series/conversion.py
kontrol/frequency_series/costs.py
kontrol/frequency_series/frequency_series.py
kontrol/frequency_series/noise_models.py
kontrol/regulator/__init__.py
kontrol/regulator/feedback.py
kontrol/regulator/oscillator.py
kontrol/regulator/post_filter.py
kontrol/regulator/predefined.py
kontrol/sensact/__init__.py
kontrol/sensact/calibration.py
kontrol/sensact/matrix.py
kontrol/sensact/optical_lever.py
kontrol/transfer_function/__init__.py
kontrol/transfer_function/notch.py
kontrol/transfer_function/transfer_function.py
kontrol-1.1.0.dist-info/LICENSE
kontrol-1.1.0.dist-info/METADATA
kontrol-1.1.0.dist-info/WHEEL
kontrol-1.1.0.dist-info/top_level.txt
kontrol-1.1.0.dist-info/RECORD
