Metadata-Version: 2.1
Name: kontrol
Version: 1.1.0
Summary: KAGRA control python package
Home-page: https://github.com/terrencetec/kontrol
Author: TSANG Terrence Tak Lun
Author-email: ttltsang@link.cuhk.edu.hk
Classifier: Programming Language :: Python :: 3
Classifier: License :: OSI Approved :: MIT License
Classifier: Operating System :: OS Independent
Requires-Python: >=3.6
License-File: LICENSE
Requires-Dist: numpy
Requires-Dist: scipy
Requires-Dist: matplotlib
Requires-Dist: control (>=0.9)
